cargan/__init__.py
cargan/__main__.py
cargan/constants.py
cargan/core.py
cargan/load.py
cargan/partition.py
cargan/train.py
cargan/assets/checkpoints/cargan.pt
cargan/assets/partitions/cumsum.json
cargan/assets/partitions/daps.json
cargan/assets/partitions/musdb.json
cargan/assets/partitions/vctk.json
cargan/data/__init__.py
cargan/data/collate.py
cargan/data/dataset.py
cargan/data/download.py
cargan/data/loader.py
cargan/data/util.py
cargan/evaluate/__init__.py
cargan/evaluate/objective/__init__.py
cargan/evaluate/objective/__main__.py
cargan/evaluate/objective/core.py
cargan/evaluate/objective/metrics.py
cargan/evaluate/receptive_field/__init__.py
cargan/evaluate/receptive_field/__main__.py
cargan/evaluate/subjective/__init__.py
cargan/evaluate/subjective/__main__.py
cargan/loss/__init__.py
cargan/loss/pitch.py
cargan/model/__init__.py
cargan/model/condition.py
cargan/model/pitch.py
cargan/model/gantts/__init__.py
cargan/model/gantts/generator.py
cargan/model/hifigan/__init__.py
cargan/model/hifigan/discriminator.py
cargan/model/hifigan/generator.py
cargan/preprocess/__init__.py
cargan/preprocess/__main__.py
cargan/preprocess/core.py
cargan/preprocess/mels.py
cargan/preprocess/pitch.py
cargan-0.0.4.dist-info/LICENSE
cargan-0.0.4.dist-info/METADATA
cargan-0.0.4.dist-info/WHEEL
cargan-0.0.4.dist-info/top_level.txt
cargan-0.0.4.dist-info/RECORD
