Metadata-Version: 2.1
Name: cargan
Version: 0.0.4
Summary: Chunked Autoregressive GAN for Conditional Waveform Synthesis
Home-page: https://github.com/descriptinc/cargan
Author: Max Morrison
Author-email: maxrmorrison@gmail.com
License: UNKNOWN
Keywords: audio,speech,gan,pytorch,vocoder
Platform: UNKNOWN
License-File: LICENSE
Requires-Dist: librosa
Requires-Dist: numpy
Requires-Dist: torch
Requires-Dist: torchaudio
Requires-Dist: torchcrepe
Requires-Dist: tqdm
